{
  "cls_label": 4,
  "cls_name": "lobby",
  "n_components": 24,
  "rooms": [
    {
      "type": "restroom",
      "x0": 8,
      "y0": 8,
      "x1": 82,
      "y1": 114
    },
    {
      "type": "restroom",
      "x0": 8,
      "y0": 114,
      "x1": 82,
      "y1": 163
    },
    {
      "type": "restroom",
      "x0": 8,
      "y0": 163,
      "x1": 82,
      "y1": 204
    },
    {
      "type": "storage",
      "x0": 8,
      "y0": 204,
      "x1": 82,
      "y1": 248
    },
    {
      "type": "lobby",
      "x0": 82,
      "y0": 8,
      "x1": 205,
      "y1": 204
    },
    {
      "type": "corridor",
      "x0": 82,
      "y0": 204,
      "x1": 205,
      "y1": 248
    },
    {
      "type": "corridor",
      "x0": 205,
      "y0": 8,
      "x1": 248,
      "y1": 139
    },
    {
      "type": "corridor",
      "x0": 205,
      "y0": 139,
      "x1": 248,
      "y1": 248
    }
  ]
}